Metadata-Version: 1.2
Name: saasy
Version: 0.0.1
Summary: Saasy API Client
Home-page: https://github.com/pixelpassion/saasy
Author: Jens Neuhaus
Author-email: hello@pixelpassion.io
Maintainer: Jens Neuhaus
Maintainer-email: hello@pixelpassion.io
License: MIT
Platform: UNKNOWN
